mcp_config_helper/__init__.py
mcp_config_helper/server.py
mcp_config_helper-0.1.0.dist-info/METADATA
mcp_config_helper-0.1.0.dist-info/WHEEL
mcp_config_helper-0.1.0.dist-info/entry_points.txt
mcp_config_helper-0.1.0.dist-info/licenses/LICENSE
mcp_config_helper-0.1.0.dist-info/RECORD
