Metadata-Version: 2.4
Name: mcp-config-helper
Version: 0.1.0
Summary: MCP server for fetching and transforming MCP configurations into Claude CLI commands
Project-URL: Homepage, https://github.com/Iron5pider/get-mcp-cli
Project-URL: Repository, https://github.com/Iron5pider/get-mcp-cli
Project-URL: Issues, https://github.com/Iron5pider/get-mcp-cli/issues
Author-email: Armaan Sood <armaansood.business@gmail.com>
License: MIT
License-File: LICENSE
Keywords: claude,cli,configuration,mcp
Classifier: License :: OSI Approved :: MIT License
Classifier: Operating System :: OS Independent
Classifier: Programming Language :: Python :: 3
Requires-Python: >=3.10
Requires-Dist: fastmcp>=0.1.0
Requires-Dist: httpx>=0.25.0
